spatial_sites/__init__.py
spatial_sites/_version.py
spatial_sites/sites.py
spatial_sites/utils.py
spatial_sites/volumes.py
spatial_sites-0.2.1.dist-info/LICENSE
spatial_sites-0.2.1.dist-info/METADATA
spatial_sites-0.2.1.dist-info/WHEEL
spatial_sites-0.2.1.dist-info/top_level.txt
spatial_sites-0.2.1.dist-info/RECORD
